MANIFEST.in
README.rst
bootstrap.py
buildout.cfg
jpl.mcl.site.sciencedata.sublime-project
setup.py
.idea/jpl.mcl.site.sciencedata.iml
.idea/misc.xml
.idea/modules.xml
.idea/vcs.xml
.idea/workspace.xml
docs/HISTORY.txt
docs/INSTALL.txt
docs/LICENSE.txt
docs/new-types.rst
src/jpl/__init__.py
src/jpl.mcl.site.sciencedata.egg-info/PKG-INFO
src/jpl.mcl.site.sciencedata.egg-info/SOURCES.txt
src/jpl.mcl.site.sciencedata.egg-info/dependency_links.txt
src/jpl.mcl.site.sciencedata.egg-info/entry_points.txt
src/jpl.mcl.site.sciencedata.egg-info/namespace_packages.txt
src/jpl.mcl.site.sciencedata.egg-info/not-zip-safe
src/jpl.mcl.site.sciencedata.egg-info/requires.txt
src/jpl.mcl.site.sciencedata.egg-info/top_level.txt
src/jpl/mcl/__init__.py
src/jpl/mcl/site/__init__.py
src/jpl/mcl/site/sciencedata/README.rst
src/jpl/mcl/site/sciencedata/__init__.py
src/jpl/mcl/site/sciencedata/_base.py
src/jpl/mcl/site/sciencedata/_utils.py
src/jpl/mcl/site/sciencedata/configure.zcml
src/jpl/mcl/site/sciencedata/errors.py
src/jpl/mcl/site/sciencedata/interfaces.py
src/jpl/mcl/site/sciencedata/sciencedata.py
src/jpl/mcl/site/sciencedata/sciencedatafolder.py
src/jpl/mcl/site/sciencedata/setuphandlers.py
src/jpl/mcl/site/sciencedata/siteingestor.py
src/jpl/mcl/site/sciencedata/testing.py
src/jpl/mcl/site/sciencedata/upgrades.py
src/jpl/mcl/site/sciencedata/upgrades.zcml
src/jpl/mcl/site/sciencedata/browser/__init__.py
src/jpl/mcl/site/sciencedata/browser/configure.zcml
src/jpl/mcl/site/sciencedata/browser/settings.py
src/jpl/mcl/site/sciencedata/locales/jpl.mcl.site.sciencedata.pot
src/jpl/mcl/site/sciencedata/locales/update.sh
src/jpl/mcl/site/sciencedata/profiles/default/catalog.xml
src/jpl/mcl/site/sciencedata/profiles/default/controlpanel.xml
src/jpl/mcl/site/sciencedata/profiles/default/jpl.mcl.site.sciencedata.txt
src/jpl/mcl/site/sciencedata/profiles/default/metadata.xml
src/jpl/mcl/site/sciencedata/profiles/default/registry.xml
src/jpl/mcl/site/sciencedata/profiles/default/types.xml
src/jpl/mcl/site/sciencedata/profiles/default/types/jpl.mcl.site.sciencedata.sciencedata.xml
src/jpl/mcl/site/sciencedata/profiles/default/types/jpl.mcl.site.sciencedata.sciencedatafolder.xml
src/jpl/mcl/site/sciencedata/sciencedata_templates/view.pt
src/jpl/mcl/site/sciencedata/sciencedatafolder_templates/view.pt
src/jpl/mcl/site/sciencedata/siteingestor_templates/siteingestor.pt
