Metadata-Version: 1.1
Name: jpl.mcl.site.sciencedata
Version: 0.0.5
Summary: Science data for the MCL site
Home-page: https://github.com/MCLConsortium/jpl.mcl.site.sciencedata
Author: Sean Kelly
Author-email: sean.kelly@jpl.nasa.gov
License: Proprietary
Download-URL: https://github.com/MCLConsortium/jpl.mcl.site.sciencedata/archive/0.0.5.zip
Keywords: plone zope science data mcl
Platform: UNKNOWN
Classifier: Development Status :: 2 - Pre-Alpha
Classifier: Environment :: Web Environment
Classifier: Framework :: Plone
Classifier: License :: Other/Proprietary License
Classifier: Operating System :: OS Independent
Classifier: Programming Language :: Python
Classifier: Topic :: Internet :: WWW/HTTP
Classifier: Topic :: Software Development :: Libraries :: Python Modules
